{
  "_comment": "Standardized Storyboard Template v2.0 - Based on 'Deep Segmentation' Schema",
  "_schema_info": {
    "segment_index": "Integer (1-based index)",
    "prompt_text": "String. Strict formatting: [Style Tags...]; Scene Description; [Character] Action/Dialogue",
    "image_url": "String or Null (Optional reference image)",
    "asset": {
      "characters": "Array of Strings (e.g., ['[CharacterName]'])",
      "scene": "String (Scene Header/Location)",
      "props": "Array of Strings (Key objects/VFX elements)"
    },
    "duration_seconds": "Integer (Duration of this specific segment)",
    "is_pro": "Boolean (Always true for this schema)",
    "resolution": "String ('horizontal' or 'vertical')"
  },
  "segments": [
    {
      "segment_index": 1,
      "prompt_text": "[Style Tags：art(...), animation(...)；风格：StyleName；场景：Location Description；镜头：Camera/Action Description containing [Character] and \"Dialogue\" and (Emotion)；SFX：Sound Effects]",
      "image_url": null,
      "asset": {
        "characters": [
          "[CharacterName]"
        ],
        "scene": "Location-TIME",
        "props": [
          "Prop1",
          "Prop2"
        ]
      },
      "duration_seconds": 5,
      "is_pro": true,
      "resolution": "horizontal"
    }
  ]
}